swagware/__init__.py
swagware/terminal.py
swagware-0.0.4.dist-info/LICENSE
swagware-0.0.4.dist-info/METADATA
swagware-0.0.4.dist-info/WHEEL
swagware-0.0.4.dist-info/top_level.txt
swagware-0.0.4.dist-info/RECORD
