Metadata-Version: 2.1
Name: swagware
Version: 0.0.4
Summary: A Python Library for cool swaggers (with rizz)
Author: codestantin
License: MIT
Project-URL: GitHub, https://github.com/codestantindev/swagware
Keywords: swag,swaggy,nobitches
Classifier: Development Status :: 4 - Beta
Classifier: License :: OSI Approved :: MIT License
Classifier: Intended Audience :: Developers
Classifier: Operating System :: OS Independent
Classifier: Programming Language :: Python :: 3.9
Classifier: Programming Language :: Python :: 3.10
Classifier: Programming Language :: Python :: 3.11
Classifier: Programming Language :: Python :: 3.12
Requires-Python: >=3.9
License-File: LICENSE
Requires-Dist: aiohttp
Requires-Dist: pystyle
